galini_io/__init__.py
galini_io/__version__.py
galini_io/logging.py
galini_io/message.py
galini_io/message_pb2.py
galini_io/reader.py
galini_io/writer.py
galini_io/scripts/__init__.py
galini_io/scripts/fake_solver.py
galini_io/scripts/reader.py
galini_io/scripts/writer.py
galini_io-0.3.1.dist-info/METADATA
galini_io-0.3.1.dist-info/RECORD
galini_io-0.3.1.dist-info/WHEEL
galini_io-0.3.1.dist-info/entry_points.txt
galini_io-0.3.1.dist-info/top_level.txt
