Metadata-Version: 2.1
Name: galini-io
Version: 0.3.1
Summary: GALINI io module
Home-page: UNKNOWN
Author: Francesco Ceccon
Author-email: francesco@ceccon.me
License: Apache 2.0
Platform: UNKNOWN
Requires-Dist: protobuf (>=3.6.1)
Requires-Dist: h5py
Requires-Dist: networkx (>=2.2)
